librefi/__init__.py
librefi/__main__.py
librefi/compat.py
librefi/librefi.py
librefi/logger.py
librefi/utils.py
librefi/version.py
librefi/connectors/__init__.py
librefi/connectors/networkmanager.py
librefi/fxckers/__init__.py
librefi/fxckers/_common.py
librefi/fxckers/_dummy.py
librefi/fxckers/_map.py
librefi/fxckers/ipartners.py
librefi/fxckers/justwifi.py
librefi/fxckers/kfchotspot.py
librefi/fxckers/ledatel.py
librefi/fxckers/umwarszawa.py
librefi-2020.12.4.dist-info/LICENSE
librefi-2020.12.4.dist-info/METADATA
librefi-2020.12.4.dist-info/WHEEL
librefi-2020.12.4.dist-info/entry_points.txt
librefi-2020.12.4.dist-info/top_level.txt
librefi-2020.12.4.dist-info/RECORD
